mcp_logger_utils/__init__.py
mcp_logger_utils/debug_tools.py
mcp_logger_utils/enhanced_logger.py
mcp_logger_utils/json_utils.py
mcp_logger_utils/logger.py
mcp_logger_utils/logger.py.backup
mcp_logger_utils/logger_backup.py
mcp_logger_utils/response_utils.py
mcp_logger_utils-0.3.0.dist-info/METADATA
mcp_logger_utils-0.3.0.dist-info/WHEEL
mcp_logger_utils-0.3.0.dist-info/licenses/LICENSE
mcp_logger_utils-0.3.0.dist-info/RECORD
