Metadata-Version: 2.4
Name: mcp-logger-utils
Version: 0.3.0
Summary: Shared utilities for MCP servers, including robust logging, JSON repair, and debug tools with automatic cache clearing.
Project-URL: Homepage, https://github.com/grahamannetts/mcp-logger-utils
Project-URL: Repository, https://github.com/grahamannetts/mcp-logger-utils
Project-URL: Bug Tracker, https://github.com/grahamannetts/mcp-logger-utils/issues
Project-URL: Documentation, https://github.com/grahamannetts/mcp-logger-utils#readme
Author-email: Graham Anderson <graham@grahama.co>
License: MIT
License-File: LICENSE
Keywords: debugging,json-repair,logging,mcp,model-context-protocol
Classifier: Development Status :: 4 - Beta
Classifier: Intended Audience :: Developers
Classifier: License :: OSI Approved :: MIT License
Classifier: Programming Language :: Python :: 3
Classifier: Programming Language :: Python :: 3.8
Classifier: Programming Language :: Python :: 3.9
Classifier: Programming Language :: Python :: 3.10
Classifier: Programming Language :: Python :: 3.11
Classifier: Programming Language :: Python :: 3.12
Classifier: Topic :: Software Development :: Libraries :: Python Modules
Classifier: Topic :: System :: Logging
Requires-Python: >=3.8
Requires-Dist: json-repair>=0.19.0
Requires-Dist: loguru>=0.7.0
Requires-Dist: psutil>=5.9.0
